nbt/__init__.py
nbt/chunk.py
nbt/nbt.py
nbt/region.py
nbt/world.py
nbt_legacy-1.5.1.dist-info/LICENSE.txt
nbt_legacy-1.5.1.dist-info/METADATA
nbt_legacy-1.5.1.dist-info/WHEEL
nbt_legacy-1.5.1.dist-info/top_level.txt
nbt_legacy-1.5.1.dist-info/RECORD
