Metadata-Version: 2.1
Name: nbt-legacy
Version: 1.5.1
Summary: Named Binary Tag Reader/Writer
Home-page: http://github.com/Netherwhal/NBT
Author: Netherwhal
Author-email: mail@netherwhal.com
License: Copyright (c) 2010-2013 Thomas Woolford and contributors        
Platform: UNKNOWN
Classifier: Development Status :: 5 - Production/Stable
Classifier: Intended Audience :: Developers
Classifier: License :: OSI Approved :: MIT License
Classifier: Operating System :: OS Independent
Classifier: Programming Language :: Python
Classifier: Programming Language :: Python :: 3.7
Classifier: Programming Language :: Python :: 3.8
Classifier: Programming Language :: Python :: 3.9
Classifier: Programming Language :: Python :: 3.10
Classifier: Topic :: Games/Entertainment
Classifier: Topic :: Software Development :: Libraries :: Python Modules
License-File: LICENSE.txt
Requires-Dist: mutf8
